waitless/__init__.py
waitless/__main__.py
waitless/config.py
waitless/diagnostics.py
waitless/engine.py
waitless/exceptions.py
waitless/instrumentation.py
waitless/selenium_integration.py
waitless/signals.py
waitless/adapters/__init__.py
waitless/adapters/angular.py
waitless/adapters/base.py
waitless/adapters/react.py
waitless/adapters/vue.py
waitless-1.0.0.dist-info/licenses/LICENSE
waitless-1.0.0.dist-info/METADATA
waitless-1.0.0.dist-info/WHEEL
waitless-1.0.0.dist-info/entry_points.txt
waitless-1.0.0.dist-info/top_level.txt
waitless-1.0.0.dist-info/RECORD
