Metadata-Version: 2.4
Name: waitless
Version: 1.0.0
Summary: Eliminate explicit waits in UI automation by detecting true UI stability
Author-email: Dhiraj Das <dhirajdas.666@gmail.com>
License: MIT
Project-URL: Homepage, https://www.dhirajdas.dev
Project-URL: Documentation, https://github.com/godhiraj-code/waitless#readme
Project-URL: Repository, https://github.com/godhiraj-code/waitless.git
Project-URL: Issues, https://github.com/godhiraj-code/waitless/issues
Keywords: selenium,automation,testing,ui-testing,wait,stability,flaky-tests
Classifier: Development Status :: 4 - Beta
Classifier: Intended Audience :: Developers
Classifier: License :: OSI Approved :: MIT License
Classifier: Operating System :: OS Independent
Classifier: Programming Language :: Python :: 3
Classifier: Programming Language :: Python :: 3.9
Classifier: Programming Language :: Python :: 3.10
Classifier: Programming Language :: Python :: 3.11
Classifier: Programming Language :: Python :: 3.12
Classifier: Topic :: Software Development :: Testing
Classifier: Topic :: Software Development :: Quality Assurance
Requires-Python: >=3.9
License-File: LICENSE
Provides-Extra: dev
Requires-Dist: pytest>=7.0; extra == "dev"
Requires-Dist: selenium>=4.0; extra == "dev"
Dynamic: license-file
